gstreamer_cli-1.27.90.data/purelib/gstreamer_cli/__init__.py
gstreamer_cli-1.27.90.data/purelib/gstreamer_cli/entrypoints.py
gstreamer_cli-1.27.90.data/purelib/gstreamer_cli/bin/ges-launch-1.0.exe
gstreamer_cli-1.27.90.data/purelib/gstreamer_cli/bin/gst-device-monitor-1.0.exe
gstreamer_cli-1.27.90.data/purelib/gstreamer_cli/bin/gst-discoverer-1.0.exe
gstreamer_cli-1.27.90.data/purelib/gstreamer_cli/bin/gst-dots-viewer.exe
gstreamer_cli-1.27.90.data/purelib/gstreamer_cli/bin/gst-inspect-1.0.exe
gstreamer_cli-1.27.90.data/purelib/gstreamer_cli/bin/gst-launch-1.0.exe
gstreamer_cli-1.27.90.data/purelib/gstreamer_cli/bin/gst-play-1.0.exe
gstreamer_cli-1.27.90.data/purelib/gstreamer_cli/bin/gst-typefind-1.0.exe
gstreamer_cli-1.27.90.data/purelib/gstreamer_cli/bin/gst-validate-1.0.exe
gstreamer_cli-1.27.90.data/purelib/gstreamer_cli/bin/gst-validate-media-check-1.0.exe
gstreamer_cli-1.27.90.data/purelib/gstreamer_cli/bin/gst-validate-rtsp-server-1.0.exe
gstreamer_cli-1.27.90.data/purelib/gstreamer_cli/bin/gst-validate-transcoding-1.0.exe
gstreamer_cli-1.27.90.dist-info/METADATA
gstreamer_cli-1.27.90.dist-info/WHEEL
gstreamer_cli-1.27.90.dist-info/entry_points.txt
gstreamer_cli-1.27.90.dist-info/top_level.txt
gstreamer_cli-1.27.90.dist-info/RECORD
